beef/__init__.py
beef/beef.py
beef/pool.py
beef/test/sample_workers.py
beef/test/test_beef.py
beef/test/test_beef2.py
beef/test/test_pool.py
pybeef-0.0.14.dist-info/METADATA
pybeef-0.0.14.dist-info/WHEEL
pybeef-0.0.14.dist-info/licenses/LICENSE
pybeef-0.0.14.dist-info/RECORD
