Metadata-Version: 2.4
Name: pybeef
Version: 0.0.14
Summary: Opinionated distributed RPC using AMQP workers
Project-URL: Homepage, https://github.com/innodatalabs/pybeef
Project-URL: Bug Tracker, https://github.com/pypa/innodatalabs/pybeef
Author-email: Mike Kroutikov <mkroutikov@innodata.com>
License-File: LICENSE
Classifier: License :: OSI Approved :: MIT License
Classifier: Operating System :: OS Independent
Classifier: Programming Language :: Python :: 3
Requires-Python: >=3.9
Requires-Dist: aio-pika~=9.0.5
Provides-Extra: test
Requires-Dist: build; extra == 'test'
Requires-Dist: pytest; extra == 'test'
Requires-Dist: pytest-aiohttp; extra == 'test'
Requires-Dist: pytest-asyncio; extra == 'test'
Requires-Dist: twine; extra == 'test'
